agnt_smth/__init__.py
agnt_smth/core/__init__.py
agnt_smth/core/agnts/__init__.py
agnt_smth/core/agnts/agnt_factory.py
agnt_smth/core/agnts/agnt_state.py
agnt_smth/core/agnts/agnt_utls.py
agnt_smth/core/data/__init__.py
agnt_smth/core/data/chroma_client.py
agnt_smth/core/prompts/__init__.py
agnt_smth/core/prompts/sys_prompts.py
agnt_smth/core/tools/__init__.py
agnt_smth/core/tools/context_retrieval.py
agnt_smth/core/tools/dotnet.py
agnt_smth/core/tools/io.py
agnt_smth/core/tools/map_yml_to_json_tool.py
agnt_smth/core/tools/mermaid.py
agnt_smth/core/tools/sh.py
agnt_smth/core/utls/__init__.py
agnt_smth/core/utls/chroma_utls.py
agnt_smth/core/utls/config_loader.py
agnt_smth/core/utls/env.py
agnt_smth/core/utls/hash.py
agnt_smth/core/utls/io.py
agnt_smth/core/utls/logger_utls.py
agnt_smth/core/utls/model_factory.py
agnt_smth/core/utls/retriever_factory.py
agnt_smth/core/utls/sh.py
agnt_smth/core/workflows/__init__.py
agnt_smth/core/workflows/builder.py
agnt_smth/vectors/__init__.py
agnt_smth/vectors/embedding_utls.py
agnt_smth-0.5.0.dist-info/LICENSE
agnt_smth-0.5.0.dist-info/METADATA
agnt_smth-0.5.0.dist-info/WHEEL
agnt_smth-0.5.0.dist-info/top_level.txt
agnt_smth-0.5.0.dist-info/RECORD
