Metadata-Version: 2.1
Name: agnt_smth
Version: 0.5.0
Summary: A simple agentic workflow builder framework, ontop of LangChain and LangGraph.
Home-page: https://github.com/stiproot/agnt-smth
Author: Simon Stipcich
Author-email: stipcich.simon@gmail.com
License: MIT
Keywords: python,package,langchain,langgraph,agentic,beta
Classifier: Intended Audience :: Developers
Classifier: License :: OSI Approved :: MIT License
Classifier: Programming Language :: Python :: 3.12
License-File: LICENSE
Requires-Dist: environs
Requires-Dist: langchain
Requires-Dist: langchain-community
Requires-Dist: langchain-chroma
Requires-Dist: langchain-openai
Requires-Dist: bs4
Requires-Dist: chromadb
Requires-Dist: langgraph
Requires-Dist: IPython
Requires-Dist: pydantic
Requires-Dist: rich
